{
    "num_iterations": 30,
    "cpu_validation": false,
    "random_init": false,
    "benchmarks": {
        "b6m": {
            "1600000": {
                "2": {
                    "64": {
                        "async": {
                            "with-const": {
                                "always-new": {
                                    "disjoint": {
                                        "round-robin": {
                                            "none": {
                                                "false": {
                                                    "false": {
                                                        "false": {
                                                            "false": {
                                                                "false": {
                                                                    "32,8": [
                                                                        {
                                                                            "phases": [
                                                                                {
                                                                                    "name": "allocation",
                                                                                    "time_sec": 3.22724653
                                                                                },
                                                                                {
                                                                                    "name": "initialization",
                                                                                    "time_sec": 53.541281869
                                                                                },
                                                                                {
                                                                                    "name": "reset_result",
                                                                                    "time_sec": 40.092078218
                                                                                }
                                                                            ],
                                                                            "iteration": 0,
                                                                            "time_phases": false,
                                                                            "computation_sec": 3.272890353,
                                                                            "gpu_result": 0,
                                                                            "total_time_sec": 100.158222763,
                                                                            "overhead_sec": 100.158222763,
                                                                            "computation_sum_phases_sec": 0
                                                                        },
                                                                        {
                                                                            "phases": [
                                                                                {
                                                                                    "name": "reset_result",
                                                                                    "time_sec": 41.215864544
                                                                                }
                                                                            ],
                                                                            "iteration": 1,
                                                                            "time_phases": false,
                                                                            "computation_sec": 2.006677052,
                                                                            "gpu_result": 0,
                                                                            "total_time_sec": 43.229644541,
                                                                            "overhead_sec": 43.229644541,
                                                                            "computation_sum_phases_sec": 0
                                                                        },
                                                                        {
                                                                            "phases": [
                                                                                {
                                                                                    "name": "reset_result",
                                                                                    "time_sec": 41.484189528
                                                                                }
                                                                            ],
                                                                            "iteration": 2,
                                                                            "time_phases": false,
                                                                            "computation_sec": 1.956648007,
                                                                            "gpu_result": 0,
                                                                            "total_time_sec": 43.446214667,
                                                                            "overhead_sec": 43.446214667,
                                                                            "computation_sum_phases_sec": 0
                                                                        },
                                                                        {
                                                                            "phases": [
                                                                                {
                                                                                    "name": "reset_result",
                                                                                    "time_sec": 41.655062807
                                                                                }
                                                                            ],
                                                                            "iteration": 3,
                                                                            "time_phases": false,
                                                                            "computation_sec": 2.014380042,
                                                                            "gpu_result": 0,
                                                                            "total_time_sec": 43.675070923,
                                                                            "overhead_sec": 43.675070923,
                                                                            "computation_sum_phases_sec": 0
                                                                        },
                                                                        {
                                                                            "phases": [
                                                                                {
                                                                                    "name": "reset_result",
                                                                                    "time_sec": 41.440550791
                                                                                }
                                                                            ],
                                                                            "iteration": 4,
                                                                            "time_phases": false,
                                                                            "computation_sec": 2.002561143,
                                                                            "gpu_result": 0,
                                                                            "total_time_sec": 43.449961734,
                                                                            "overhead_sec": 43.449961734,
                                                                            "computation_sum_phases_sec": 0
                                                                        },
                                                                        {
                                                                            "phases": [
                                                                                {
                                                                                    "name": "reset_result",
                                                                                    "time_sec": 41.814567967
                                                                                }
                                                                            ],
                                                                            "iteration": 5,
                                                                            "time_phases": false,
                                                                            "computation_sec": 2.053676111,
                                                                            "gpu_result": 0,
                                                                            "total_time_sec": 43.872457005,
                                                                            "overhead_sec": 43.872457005,
                                                                            "computation_sum_phases_sec": 0
                                                                        },
                                                                        {
                                                                            "phases": [
                                                                                {
                                                                                    "name": "reset_result",
                                                                                    "time_sec": 41.12363818
                                                                                }
                                                                            ],
                                                                            "iteration": 6,
                                                                            "time_phases": false,
                                                                            "computation_sec": 1.952115162,
                                                                            "gpu_result": 0,
                                                                            "total_time_sec": 43.078467038,
                                                                            "overhead_sec": 43.078467038,
                                                                            "computation_sum_phases_sec": 0
                                                                        },
                                                                        {
                                                                            "phases": [
                                                                                {
                                                                                    "name": "reset_result",
                                                                                    "time_sec": 41.061148905
                                                                                }
                                                                            ],
                                                                            "iteration": 7,
                                                                            "time_phases": false,
                                                                            "computation_sec": 1.981155932,
                                                                            "gpu_result": 0,
                                                                            "total_time_sec": 43.045095014,
                                                                            "overhead_sec": 43.045095014,
                                                                            "computation_sum_phases_sec": 0
                                                                        },
                                                                        {
                                                                            "phases": [
                                                                                {
                                                                                    "name": "reset_result",
                                                                                    "time_sec": 40.852092197
                                                                                }
                                                                            ],
                                                                            "iteration": 8,
                                                                            "time_phases": false,
                                                                            "computation_sec": 1.962433529,
                                                                            "gpu_result": 0,
                                                                            "total_time_sec": 42.817434364,
                                                                            "overhead_sec": 42.817434364,
                                                                            "computation_sum_phases_sec": 0
                                                                        },
                                                                        {
                                                                            "phases": [
                                                                                {
                                                                                    "name": "reset_result",
                                                                                    "time_sec": 41.05488706
                                                                                }
                                                                            ],
                                                                            "iteration": 9,
                                                                            "time_phases": false,
                                                                            "computation_sec": 1.952308948,
                                                                            "gpu_result": 0,
                                                                            "total_time_sec": 43.010007423,
                                                                            "overhead_sec": 43.010007423,
                                                                            "computation_sum_phases_sec": 0
                                                                        },
                                                                        {
                                                                            "phases": [
                                                                                {
                                                                                    "name": "reset_result",
                                                                                    "time_sec": 41.067917355
                                                                                }
                                                                            ],
                                                                            "iteration": 10,
                                                                            "time_phases": false,
                                                                            "computation_sec": 1.923736117,
                                                                            "gpu_result": 0,
                                                                            "total_time_sec": 42.994046269,
                                                                            "overhead_sec": 42.994046269,
                                                                            "computation_sum_phases_sec": 0
                                                                        },
                                                                        {
                                                                            "phases": [
                                                                                {
                                                                                    "name": "reset_result",
                                                                                    "time_sec": 40.584452464
                                                                                }
                                                                            ],
                                                                            "iteration": 11,
                                                                            "time_phases": false,
                                                                            "computation_sec": 1.944480394,
                                                                            "gpu_result": 0,
                                                                            "total_time_sec": 42.531206108,
                                                                            "overhead_sec": 42.531206108,
                                                                            "computation_sum_phases_sec": 0
                                                                        },
                                                                        {
                                                                            "phases": [
                                                                                {
                                                                                    "name": "reset_result",
                                                                                    "time_sec": 40.917479916
                                                                                }
                                                                            ],
                                                                            "iteration": 12,
                                                                            "time_phases": false,
                                                                            "computation_sec": 1.961808371,
                                                                            "gpu_result": 0,
                                                                            "total_time_sec": 42.881999854,
                                                                            "overhead_sec": 42.881999854,
                                                                            "computation_sum_phases_sec": 0
                                                                        },
                                                                        {
                                                                            "phases": [
                                                                                {
                                                                                    "name": "reset_result",
                                                                                    "time_sec": 41.173061721
                                                                                }
                                                                            ],
                                                                            "iteration": 13,
                                                                            "time_phases": false,
                                                                            "computation_sec": 1.950804169,
                                                                            "gpu_result": 0,
                                                                            "total_time_sec": 43.126648842,
                                                                            "overhead_sec": 43.126648842,
                                                                            "computation_sum_phases_sec": 0
                                                                        },
                                                                        {
                                                                            "phases": [
                                                                                {
                                                                                    "name": "reset_result",
                                                                                    "time_sec": 41.238591936
                                                                                }
                                                                            ],
                                                                            "iteration": 14,
                                                                            "time_phases": false,
                                                                            "computation_sec": 1.96287513,
                                                                            "gpu_result": 0,
                                                                            "total_time_sec": 43.203757501,
                                                                            "overhead_sec": 43.203757501,
                                                                            "computation_sum_phases_sec": 0
                                                                        },
                                                                        {
                                                                            "phases": [
                                                                                {
                                                                                    "name": "reset_result",
                                                                                    "time_sec": 41.194096547
                                                                                }
                                                                            ],
                                                                            "iteration": 15,
                                                                            "time_phases": false,
                                                                            "computation_sec": 1.994187562,
                                                                            "gpu_result": 0,
                                                                            "total_time_sec": 43.190464245,
                                                                            "overhead_sec": 43.190464245,
                                                                            "computation_sum_phases_sec": 0
                                                                        },
                                                                        {
                                                                            "phases": [
                                                                                {
                                                                                    "name": "reset_result",
                                                                                    "time_sec": 41.085172603
                                                                                }
                                                                            ],
                                                                            "iteration": 16,
                                                                            "time_phases": false,
                                                                            "computation_sec": 1.983587869,
                                                                            "gpu_result": 0,
                                                                            "total_time_sec": 43.07107628,
                                                                            "overhead_sec": 43.07107628,
                                                                            "computation_sum_phases_sec": 0
                                                                        },
                                                                        {
                                                                            "phases": [
                                                                                {
                                                                                    "name": "reset_result",
                                                                                    "time_sec": 41.306082874
                                                                                }
                                                                            ],
                                                                            "iteration": 17,
                                                                            "time_phases": false,
                                                                            "computation_sec": 2.008136906,
                                                                            "gpu_result": 0,
                                                                            "total_time_sec": 43.316458567,
                                                                            "overhead_sec": 43.316458567,
                                                                            "computation_sum_phases_sec": 0
                                                                        },
                                                                        {
                                                                            "phases": [
                                                                                {
                                                                                    "name": "reset_result",
                                                                                    "time_sec": 41.877979108
                                                                                }
                                                                            ],
                                                                            "iteration": 18,
                                                                            "time_phases": false,
                                                                            "computation_sec": 1.964062176,
                                                                            "gpu_result": 0,
                                                                            "total_time_sec": 43.844412505,
                                                                            "overhead_sec": 43.844412505,
                                                                            "computation_sum_phases_sec": 0
                                                                        },
                                                                        {
                                                                            "phases": [
                                                                                {
                                                                                    "name": "reset_result",
                                                                                    "time_sec": 41.807810055
                                                                                }
                                                                            ],
                                                                            "iteration": 19,
                                                                            "time_phases": false,
                                                                            "computation_sec": 1.98570076,
                                                                            "gpu_result": 0,
                                                                            "total_time_sec": 43.79571068,
                                                                            "overhead_sec": 43.79571068,
                                                                            "computation_sum_phases_sec": 0
                                                                        },
                                                                        {
                                                                            "phases": [
                                                                                {
                                                                                    "name": "reset_result",
                                                                                    "time_sec": 42.207152111
                                                                                }
                                                                            ],
                                                                            "iteration": 20,
                                                                            "time_phases": false,
                                                                            "computation_sec": 1.97485123,
                                                                            "gpu_result": 0,
                                                                            "total_time_sec": 44.184803613,
                                                                            "overhead_sec": 44.184803613,
                                                                            "computation_sum_phases_sec": 0
                                                                        },
                                                                        {
                                                                            "phases": [
                                                                                {
                                                                                    "name": "reset_result",
                                                                                    "time_sec": 41.876864937
                                                                                }
                                                                            ],
                                                                            "iteration": 21,
                                                                            "time_phases": false,
                                                                            "computation_sec": 1.895964432,
                                                                            "gpu_result": 0,
                                                                            "total_time_sec": 43.774842658,
                                                                            "overhead_sec": 43.774842658,
                                                                            "computation_sum_phases_sec": 0
                                                                        },
                                                                        {
                                                                            "phases": [
                                                                                {
                                                                                    "name": "reset_result",
                                                                                    "time_sec": 41.872965669
                                                                                }
                                                                            ],
                                                                            "iteration": 22,
                                                                            "time_phases": false,
                                                                            "computation_sec": 1.995002608,
                                                                            "gpu_result": 0,
                                                                            "total_time_sec": 43.870586046,
                                                                            "overhead_sec": 43.870586046,
                                                                            "computation_sum_phases_sec": 0
                                                                        },
                                                                        {
                                                                            "phases": [
                                                                                {
                                                                                    "name": "reset_result",
                                                                                    "time_sec": 41.479134372
                                                                                }
                                                                            ],
                                                                            "iteration": 23,
                                                                            "time_phases": false,
                                                                            "computation_sec": 2.023988395,
                                                                            "gpu_result": 0,
                                                                            "total_time_sec": 43.505143527,
                                                                            "overhead_sec": 43.505143527,
                                                                            "computation_sum_phases_sec": 0
                                                                        },
                                                                        {
                                                                            "phases": [
                                                                                {
                                                                                    "name": "reset_result",
                                                                                    "time_sec": 41.661443613
                                                                                }
                                                                            ],
                                                                            "iteration": 24,
                                                                            "time_phases": false,
                                                                            "computation_sec": 1.953407369,
                                                                            "gpu_result": 0,
                                                                            "total_time_sec": 43.617692632,
                                                                            "overhead_sec": 43.617692632,
                                                                            "computation_sum_phases_sec": 0
                                                                        },
                                                                        {
                                                                            "phases": [
                                                                                {
                                                                                    "name": "reset_result",
                                                                                    "time_sec": 41.734406048
                                                                                }
                                                                            ],
                                                                            "iteration": 25,
                                                                            "time_phases": false,
                                                                            "computation_sec": 1.96438876,
                                                                            "gpu_result": 0,
                                                                            "total_time_sec": 43.700632898,
                                                                            "overhead_sec": 43.700632898,
                                                                            "computation_sum_phases_sec": 0
                                                                        },
                                                                        {
                                                                            "phases": [
                                                                                {
                                                                                    "name": "reset_result",
                                                                                    "time_sec": 41.844106144
                                                                                }
                                                                            ],
                                                                            "iteration": 26,
                                                                            "time_phases": false,
                                                                            "computation_sec": 2.005670219,
                                                                            "gpu_result": 0,
                                                                            "total_time_sec": 43.851532657,
                                                                            "overhead_sec": 43.851532657,
                                                                            "computation_sum_phases_sec": 0
                                                                        },
                                                                        {
                                                                            "phases": [
                                                                                {
                                                                                    "name": "reset_result",
                                                                                    "time_sec": 41.762238888
                                                                                }
                                                                            ],
                                                                            "iteration": 27,
                                                                            "time_phases": false,
                                                                            "computation_sec": 1.984521737,
                                                                            "gpu_result": 0,
                                                                            "total_time_sec": 43.748602418,
                                                                            "overhead_sec": 43.748602418,
                                                                            "computation_sum_phases_sec": 0
                                                                        },
                                                                        {
                                                                            "phases": [
                                                                                {
                                                                                    "name": "reset_result",
                                                                                    "time_sec": 41.568986988
                                                                                }
                                                                            ],
                                                                            "iteration": 28,
                                                                            "time_phases": false,
                                                                            "computation_sec": 1.957204144,
                                                                            "gpu_result": 0,
                                                                            "total_time_sec": 43.528419059,
                                                                            "overhead_sec": 43.528419059,
                                                                            "computation_sum_phases_sec": 0
                                                                        },
                                                                        {
                                                                            "phases": [
                                                                                {
                                                                                    "name": "reset_result",
                                                                                    "time_sec": 41.508826611
                                                                                }
                                                                            ],
                                                                            "iteration": 29,
                                                                            "time_phases": false,
                                                                            "computation_sec": 1.967093746,
                                                                            "gpu_result": 0,
                                                                            "total_time_sec": 43.477746004,
                                                                            "overhead_sec": 43.477746004,
                                                                            "computation_sum_phases_sec": 0
                                                                        }
                                                                    ]
                                                                }
                                                            }
                                                        }
                                                    }
                                                }
                                            }
                                        }
                                    }
                                }
                            }
                        }
                    }
                }
            }
        }
    }
}